setup.py
commonutil_fileio_runtimerecord/__init__.py
commonutil_fileio_runtimerecord/processid.py
commonutil_fileio_runtimerecord/timestamp.py
commonutil_fileio_runtimerecord.egg-info/PKG-INFO
commonutil_fileio_runtimerecord.egg-info/SOURCES.txt
commonutil_fileio_runtimerecord.egg-info/dependency_links.txt
commonutil_fileio_runtimerecord.egg-info/top_level.txt
test/test_timestamp.py